setup.py
gbdx_auth/__init__.py
gbdx_auth/gbdx_auth.py
gbdx_auth.egg-info/PKG-INFO
gbdx_auth.egg-info/SOURCES.txt
gbdx_auth.egg-info/dependency_links.txt
gbdx_auth.egg-info/requires.txt
gbdx_auth.egg-info/top_level.txt