Metadata-Version: 1.1
Name: gbdx-auth
Version: 0.3.0
Summary: An Oauth2 Helper Tool for the GBDX Platform
Home-page: https://github.com/tdg-platform
Author: GBDX (Nate Ricklin)
Author-email: nate.ricklin@digitialglobe.com
License: UNKNOWN
Keywords: digitalglobe
Platform: UNKNOWN
Classifier: Development Status :: 3 - Alpha
Classifier: Intended Audience :: Developers
Classifier: Programming Language :: Python :: 2.7
